dall_e/__init__.py
dall_e/model.py
paddledalle-1.0.0.dist-info/LICENSE
paddledalle-1.0.0.dist-info/METADATA
paddledalle-1.0.0.dist-info/WHEEL
paddledalle-1.0.0.dist-info/top_level.txt
paddledalle-1.0.0.dist-info/RECORD
