Metadata-Version: 2.1
Name: paddledalle
Version: 1.0.0
Summary: Paddle DALL-E
Home-page: UNKNOWN
Author: jm12138
Author-email: 2286040843@qq.com
License: Apache-2.0 License
Platform: UNKNOWN
Requires-Dist: wget
